opsdroid_zodb/__init__.py
opsdroid_zodb/database.py
opsdroid_zodb-0.1.0.dist-info/AUTHORS.rst
opsdroid_zodb-0.1.0.dist-info/LICENSE
opsdroid_zodb-0.1.0.dist-info/METADATA
opsdroid_zodb-0.1.0.dist-info/WHEEL
opsdroid_zodb-0.1.0.dist-info/entry_points.txt
opsdroid_zodb-0.1.0.dist-info/top_level.txt
opsdroid_zodb-0.1.0.dist-info/RECORD
