Metadata-Version: 2.1
Name: opsdroid-zodb
Version: 0.1.0
Summary: ZODB support for opsdroid
Home-page: https://github.com/koodaamo/opsdroid-zodb
Author: Petri Savolainen
Author-email: petri@koodaamo.fi
License: Apache Software License 2.0
Keywords: opsdroid zodb
Platform: UNKNOWN
Classifier: Development Status :: 2 - Pre-Alpha
Classifier: Intended Audience :: Developers
Classifier: License :: OSI Approved :: Apache Software License
Classifier: Natural Language :: English
Classifier: Programming Language :: Python :: 3
Classifier: Programming Language :: Python :: 3.5
Classifier: Programming Language :: Python :: 3.6
Classifier: Programming Language :: Python :: 3.7
Requires-Dist: ZODB
